whitenoise_spa/__init__.py
whitenoise_spa/middleware.py
whitenoise_spa/py.typed
whitenoise_spa-2.0.0.dist-info/LICENSE
whitenoise_spa-2.0.0.dist-info/METADATA
whitenoise_spa-2.0.0.dist-info/WHEEL
whitenoise_spa-2.0.0.dist-info/top_level.txt
whitenoise_spa-2.0.0.dist-info/RECORD
