Metadata-Version: 2.1
Name: whitenoise-spa
Version: 2.0.0
Summary: Serve SPA (Single Page Application) in django using whitenoise
Author-email: Pradish Bijukchhe <pradish@sandbox.com.np>
License: Copyright (c) 2024 Pradish Bijukchhe
Project-URL: Homepage, https://github.com/sandbox-pokhara/whitenoise-spa
Project-URL: Issues, https://github.com/sandbox-pokhara/whitenoise-spa/issues
Classifier: Programming Language :: Python :: 3
Requires-Python: >=3
License-File: LICENSE
Requires-Dist: whitenoise
